{"dependencies":[{"name":"./calendar","loc":{"line":1,"column":32}},{"name":"./formats","loc":{"line":2,"column":38}},{"name":"./invalid","loc":{"line":3,"column":35}},{"name":"./ordinal","loc":{"line":4,"column":62}},{"name":"./relative","loc":{"line":5,"column":36}},{"name":"../units/month","loc":{"line":11,"column":7}},{"name":"../units/week","loc":{"line":14,"column":34}},{"name":"../units/day-of-week","loc":{"line":21,"column":7}},{"name":"../units/hour","loc":{"line":24,"column":43}}],"generated":{"js":"\"use strict\";\n\nObject.defineProperty(exports, \"__esModule\", {\n  value: true\n});\nexports.baseConfig = undefined;\n\nvar _calendar = require(\"./calendar\");\n\nvar _formats = require(\"./formats\");\n\nvar _invalid = require(\"./invalid\");\n\nvar _ordinal = require(\"./ordinal\");\n\nvar _relative = require(\"./relative\");\n\nvar _month = require(\"../units/month\");\n\nvar _week = require(\"../units/week\");\n\nvar _dayOfWeek = require(\"../units/day-of-week\");\n\nvar _hour = require(\"../units/hour\");\n\n// weekdays\n\n\n// months\nvar baseConfig = exports.baseConfig = {\n  calendar: _calendar.defaultCalendar,\n  longDateFormat: _formats.defaultLongDateFormat,\n  invalidDate: _invalid.defaultInvalidDate,\n  ordinal: _ordinal.defaultOrdinal,\n  dayOfMonthOrdinalParse: _ordinal.defaultDayOfMonthOrdinalParse,\n  relativeTime: _relative.defaultRelativeTime,\n\n  months: _month.defaultLocaleMonths,\n  monthsShort: _month.defaultLocaleMonthsShort,\n\n  week: _week.defaultLocaleWeek,\n\n  weekdays: _dayOfWeek.defaultLocaleWeekdays,\n  weekdaysMin: _dayOfWeek.defaultLocaleWeekdaysMin,\n  weekdaysShort: _dayOfWeek.defaultLocaleWeekdaysShort,\n\n  meridiemParse: _hour.defaultLocaleMeridiemParse\n};\n\n// meridiem\n\n\n// week"},"hash":"188014a98d9e870ad5c6cbdda66519f3"}