{"dependencies":[{"name":"./affix","loc":{"line":1,"column":33}},{"name":"./anchor","loc":{"line":2,"column":34}},{"name":"./auto-complete","loc":{"line":3,"column":40}},{"name":"./alert","loc":{"line":4,"column":33}},{"name":"./avatar","loc":{"line":5,"column":34}},{"name":"./back-top","loc":{"line":6,"column":35}},{"name":"./badge","loc":{"line":7,"column":33}},{"name":"./breadcrumb","loc":{"line":8,"column":38}},{"name":"./button","loc":{"line":9,"column":34}},{"name":"./calendar","loc":{"line":10,"column":36}},{"name":"./card","loc":{"line":11,"column":32}},{"name":"./collapse","loc":{"line":12,"column":36}},{"name":"./carousel","loc":{"line":13,"column":36}},{"name":"./cascader","loc":{"line":14,"column":36}},{"name":"./checkbox","loc":{"line":15,"column":36}},{"name":"./col","loc":{"line":16,"column":31}},{"name":"./date-picker","loc":{"line":17,"column":38}},{"name":"./divider","loc":{"line":18,"column":35}},{"name":"./dropdown","loc":{"line":19,"column":36}},{"name":"./form","loc":{"line":20,"column":32}},{"name":"./icon","loc":{"line":21,"column":32}},{"name":"./input","loc":{"line":22,"column":33}},{"name":"./input-number","loc":{"line":23,"column":39}},{"name":"./layout","loc":{"line":24,"column":34}},{"name":"./list","loc":{"line":25,"column":32}},{"name":"./locale-provider","loc":{"line":26,"column":42}},{"name":"./message","loc":{"line":27,"column":35}},{"name":"./menu","loc":{"line":28,"column":32}},{"name":"./modal","loc":{"line":29,"column":33}},{"name":"./notification","loc":{"line":30,"column":40}},{"name":"./pagination","loc":{"line":31,"column":38}},{"name":"./popconfirm","loc":{"line":32,"column":38}},{"name":"./popover","loc":{"line":33,"column":35}},{"name":"./progress","loc":{"line":34,"column":36}},{"name":"./radio","loc":{"line":35,"column":33}},{"name":"./rate","loc":{"line":36,"column":32}},{"name":"./row","loc":{"line":37,"column":31}},{"name":"./select","loc":{"line":38,"column":34}},{"name":"./slider","loc":{"line":39,"column":34}},{"name":"./spin","loc":{"line":40,"column":32}},{"name":"./steps","loc":{"line":41,"column":33}},{"name":"./switch","loc":{"line":42,"column":34}},{"name":"./table","loc":{"line":43,"column":33}},{"name":"./transfer","loc":{"line":44,"column":36}},{"name":"./tree","loc":{"line":45,"column":32}},{"name":"./tree-select","loc":{"line":46,"column":38}},{"name":"./tabs","loc":{"line":47,"column":32}},{"name":"./tag","loc":{"line":48,"column":31}},{"name":"./time-picker","loc":{"line":49,"column":38}},{"name":"./timeline","loc":{"line":50,"column":36}},{"name":"./tooltip","loc":{"line":51,"column":35}},{"name":"./mention","loc":{"line":52,"column":35}},{"name":"./upload","loc":{"line":53,"column":34}},{"name":"./version","loc":{"line":54,"column":35}}],"generated":{"js":"\"use strict\";\n\nObject.defineProperty(exports, \"__esModule\", {\n  value: true\n});\n\nvar _affix = require(\"./affix\");\n\nObject.defineProperty(exports, \"Affix\", {\n  enumerable: true,\n  get: function get() {\n    return _interopRequireDefault(_affix).default;\n  }\n});\n\nvar _anchor = require(\"./anchor\");\n\nObject.defineProperty(exports, \"Anchor\", {\n  enumerable: true,\n  get: function get() {\n    return _interopRequireDefault(_anchor).default;\n  }\n});\n\nvar _autoComplete = require(\"./auto-complete\");\n\nObject.defineProperty(exports, \"AutoComplete\", {\n  enumerable: true,\n  get: function get() {\n    return _interopRequireDefault(_autoComplete).default;\n  }\n});\n\nvar _alert = require(\"./alert\");\n\nObject.defineProperty(exports, \"Alert\", {\n  enumerable: true,\n  get: function get() {\n    return _interopRequireDefault(_alert).default;\n  }\n});\n\nvar _avatar = require(\"./avatar\");\n\nObject.defineProperty(exports, \"Avatar\", {\n  enumerable: true,\n  get: function get() {\n    return _interopRequireDefault(_avatar).default;\n  }\n});\n\nvar _backTop = require(\"./back-top\");\n\nObject.defineProperty(exports, \"BackTop\", {\n  enumerable: true,\n  get: function get() {\n    return _interopRequireDefault(_backTop).default;\n  }\n});\n\nvar _badge = require(\"./badge\");\n\nObject.defineProperty(exports, \"Badge\", {\n  enumerable: true,\n  get: function get() {\n    return _interopRequireDefault(_badge).default;\n  }\n});\n\nvar _breadcrumb = require(\"./breadcrumb\");\n\nObject.defineProperty(exports, \"Breadcrumb\", {\n  enumerable: true,\n  get: function get() {\n    return _interopRequireDefault(_breadcrumb).default;\n  }\n});\n\nvar _button = require(\"./button\");\n\nObject.defineProperty(exports, \"Button\", {\n  enumerable: true,\n  get: function get() {\n    return _interopRequireDefault(_button).default;\n  }\n});\n\nvar _calendar = require(\"./calendar\");\n\nObject.defineProperty(exports, \"Calendar\", {\n  enumerable: true,\n  get: function get() {\n    return _interopRequireDefault(_calendar).default;\n  }\n});\n\nvar _card = require(\"./card\");\n\nObject.defineProperty(exports, \"Card\", {\n  enumerable: true,\n  get: function get() {\n    return _interopRequireDefault(_card).default;\n  }\n});\n\nvar _collapse = require(\"./collapse\");\n\nObject.defineProperty(exports, \"Collapse\", {\n  enumerable: true,\n  get: function get() {\n    return _interopRequireDefault(_collapse).default;\n  }\n});\n\nvar _carousel = require(\"./carousel\");\n\nObject.defineProperty(exports, \"Carousel\", {\n  enumerable: true,\n  get: function get() {\n    return _interopRequireDefault(_carousel).default;\n  }\n});\n\nvar _cascader = require(\"./cascader\");\n\nObject.defineProperty(exports, \"Cascader\", {\n  enumerable: true,\n  get: function get() {\n    return _interopRequireDefault(_cascader).default;\n  }\n});\n\nvar _checkbox = require(\"./checkbox\");\n\nObject.defineProperty(exports, \"Checkbox\", {\n  enumerable: true,\n  get: function get() {\n    return _interopRequireDefault(_checkbox).default;\n  }\n});\n\nvar _col = require(\"./col\");\n\nObject.defineProperty(exports, \"Col\", {\n  enumerable: true,\n  get: function get() {\n    return _interopRequireDefault(_col).default;\n  }\n});\n\nvar _datePicker = require(\"./date-picker\");\n\nObject.defineProperty(exports, \"DatePicker\", {\n  enumerable: true,\n  get: function get() {\n    return _interopRequireDefault(_datePicker).default;\n  }\n});\n\nvar _divider = require(\"./divider\");\n\nObject.defineProperty(exports, \"Divider\", {\n  enumerable: true,\n  get: function get() {\n    return _interopRequireDefault(_divider).default;\n  }\n});\n\nvar _dropdown = require(\"./dropdown\");\n\nObject.defineProperty(exports, \"Dropdown\", {\n  enumerable: true,\n  get: function get() {\n    return _interopRequireDefault(_dropdown).default;\n  }\n});\n\nvar _form = require(\"./form\");\n\nObject.defineProperty(exports, \"Form\", {\n  enumerable: true,\n  get: function get() {\n    return _interopRequireDefault(_form).default;\n  }\n});\n\nvar _icon = require(\"./icon\");\n\nObject.defineProperty(exports, \"Icon\", {\n  enumerable: true,\n  get: function get() {\n    return _interopRequireDefault(_icon).default;\n  }\n});\n\nvar _input = require(\"./input\");\n\nObject.defineProperty(exports, \"Input\", {\n  enumerable: true,\n  get: function get() {\n    return _interopRequireDefault(_input).default;\n  }\n});\n\nvar _inputNumber = require(\"./input-number\");\n\nObject.defineProperty(exports, \"InputNumber\", {\n  enumerable: true,\n  get: function get() {\n    return _interopRequireDefault(_inputNumber).default;\n  }\n});\n\nvar _layout = require(\"./layout\");\n\nObject.defineProperty(exports, \"Layout\", {\n  enumerable: true,\n  get: function get() {\n    return _interopRequireDefault(_layout).default;\n  }\n});\n\nvar _list = require(\"./list\");\n\nObject.defineProperty(exports, \"List\", {\n  enumerable: true,\n  get: function get() {\n    return _interopRequireDefault(_list).default;\n  }\n});\n\nvar _localeProvider = require(\"./locale-provider\");\n\nObject.defineProperty(exports, \"LocaleProvider\", {\n  enumerable: true,\n  get: function get() {\n    return _interopRequireDefault(_localeProvider).default;\n  }\n});\n\nvar _message = require(\"./message\");\n\nObject.defineProperty(exports, \"message\", {\n  enumerable: true,\n  get: function get() {\n    return _interopRequireDefault(_message).default;\n  }\n});\n\nvar _menu = require(\"./menu\");\n\nObject.defineProperty(exports, \"Menu\", {\n  enumerable: true,\n  get: function get() {\n    return _interopRequireDefault(_menu).default;\n  }\n});\n\nvar _modal = require(\"./modal\");\n\nObject.defineProperty(exports, \"Modal\", {\n  enumerable: true,\n  get: function get() {\n    return _interopRequireDefault(_modal).default;\n  }\n});\n\nvar _notification = require(\"./notification\");\n\nObject.defineProperty(exports, \"notification\", {\n  enumerable: true,\n  get: function get() {\n    return _interopRequireDefault(_notification).default;\n  }\n});\n\nvar _pagination = require(\"./pagination\");\n\nObject.defineProperty(exports, \"Pagination\", {\n  enumerable: true,\n  get: function get() {\n    return _interopRequireDefault(_pagination).default;\n  }\n});\n\nvar _popconfirm = require(\"./popconfirm\");\n\nObject.defineProperty(exports, \"Popconfirm\", {\n  enumerable: true,\n  get: function get() {\n    return _interopRequireDefault(_popconfirm).default;\n  }\n});\n\nvar _popover = require(\"./popover\");\n\nObject.defineProperty(exports, \"Popover\", {\n  enumerable: true,\n  get: function get() {\n    return _interopRequireDefault(_popover).default;\n  }\n});\n\nvar _progress = require(\"./progress\");\n\nObject.defineProperty(exports, \"Progress\", {\n  enumerable: true,\n  get: function get() {\n    return _interopRequireDefault(_progress).default;\n  }\n});\n\nvar _radio = require(\"./radio\");\n\nObject.defineProperty(exports, \"Radio\", {\n  enumerable: true,\n  get: function get() {\n    return _interopRequireDefault(_radio).default;\n  }\n});\n\nvar _rate = require(\"./rate\");\n\nObject.defineProperty(exports, \"Rate\", {\n  enumerable: true,\n  get: function get() {\n    return _interopRequireDefault(_rate).default;\n  }\n});\n\nvar _row = require(\"./row\");\n\nObject.defineProperty(exports, \"Row\", {\n  enumerable: true,\n  get: function get() {\n    return _interopRequireDefault(_row).default;\n  }\n});\n\nvar _select = require(\"./select\");\n\nObject.defineProperty(exports, \"Select\", {\n  enumerable: true,\n  get: function get() {\n    return _interopRequireDefault(_select).default;\n  }\n});\n\nvar _slider = require(\"./slider\");\n\nObject.defineProperty(exports, \"Slider\", {\n  enumerable: true,\n  get: function get() {\n    return _interopRequireDefault(_slider).default;\n  }\n});\n\nvar _spin = require(\"./spin\");\n\nObject.defineProperty(exports, \"Spin\", {\n  enumerable: true,\n  get: function get() {\n    return _interopRequireDefault(_spin).default;\n  }\n});\n\nvar _steps = require(\"./steps\");\n\nObject.defineProperty(exports, \"Steps\", {\n  enumerable: true,\n  get: function get() {\n    return _interopRequireDefault(_steps).default;\n  }\n});\n\nvar _switch = require(\"./switch\");\n\nObject.defineProperty(exports, \"Switch\", {\n  enumerable: true,\n  get: function get() {\n    return _interopRequireDefault(_switch).default;\n  }\n});\n\nvar _table = require(\"./table\");\n\nObject.defineProperty(exports, \"Table\", {\n  enumerable: true,\n  get: function get() {\n    return _interopRequireDefault(_table).default;\n  }\n});\n\nvar _transfer = require(\"./transfer\");\n\nObject.defineProperty(exports, \"Transfer\", {\n  enumerable: true,\n  get: function get() {\n    return _interopRequireDefault(_transfer).default;\n  }\n});\n\nvar _tree = require(\"./tree\");\n\nObject.defineProperty(exports, \"Tree\", {\n  enumerable: true,\n  get: function get() {\n    return _interopRequireDefault(_tree).default;\n  }\n});\n\nvar _treeSelect = require(\"./tree-select\");\n\nObject.defineProperty(exports, \"TreeSelect\", {\n  enumerable: true,\n  get: function get() {\n    return _interopRequireDefault(_treeSelect).default;\n  }\n});\n\nvar _tabs = require(\"./tabs\");\n\nObject.defineProperty(exports, \"Tabs\", {\n  enumerable: true,\n  get: function get() {\n    return _interopRequireDefault(_tabs).default;\n  }\n});\n\nvar _tag = require(\"./tag\");\n\nObject.defineProperty(exports, \"Tag\", {\n  enumerable: true,\n  get: function get() {\n    return _interopRequireDefault(_tag).default;\n  }\n});\n\nvar _timePicker = require(\"./time-picker\");\n\nObject.defineProperty(exports, \"TimePicker\", {\n  enumerable: true,\n  get: function get() {\n    return _interopRequireDefault(_timePicker).default;\n  }\n});\n\nvar _timeline = require(\"./timeline\");\n\nObject.defineProperty(exports, \"Timeline\", {\n  enumerable: true,\n  get: function get() {\n    return _interopRequireDefault(_timeline).default;\n  }\n});\n\nvar _tooltip = require(\"./tooltip\");\n\nObject.defineProperty(exports, \"Tooltip\", {\n  enumerable: true,\n  get: function get() {\n    return _interopRequireDefault(_tooltip).default;\n  }\n});\n\nvar _mention = require(\"./mention\");\n\nObject.defineProperty(exports, \"Mention\", {\n  enumerable: true,\n  get: function get() {\n    return _interopRequireDefault(_mention).default;\n  }\n});\n\nvar _upload = require(\"./upload\");\n\nObject.defineProperty(exports, \"Upload\", {\n  enumerable: true,\n  get: function get() {\n    return _interopRequireDefault(_upload).default;\n  }\n});\n\nvar _version = require(\"./version\");\n\nObject.defineProperty(exports, \"version\", {\n  enumerable: true,\n  get: function get() {\n    return _interopRequireDefault(_version).default;\n  }\n});\n\nfunction _interopRequireDefault(obj) { return obj && obj.__esModule ? obj : { default: obj }; }"},"hash":"0035f67a860ef9a8c147eb6c2de9139a"}